pywerami/__init__.py
pywerami/api.py
pywerami/mainapp.py
pywerami/ui_pywerami.py
pywerami/images/pywerami.png
pywerami/samples/__init__.py
pywerami/samples/in17a_1.tab
pywerami/samples/luca3_1.tab
pywerami/ui/compile_ui.sh
pywerami/ui/pywerami.ui
pywerami-0.3.0.dist-info/METADATA
pywerami-0.3.0.dist-info/WHEEL
pywerami-0.3.0.dist-info/entry_points.txt
pywerami-0.3.0.dist-info/licenses/AUTHORS.md
pywerami-0.3.0.dist-info/licenses/LICENSE
pywerami-0.3.0.dist-info/RECORD
