Metadata-Version: 2.4
Name: pywerami
Version: 0.3.0
Summary: pywerami is a stand-alone program to make an countour/3D plot from a contour data file generated by the Perple_X program WERAMI.
Project-URL: Homepage, https://github.com/ondrolexa/pywerami
Project-URL: Documentation, https://pywerami.readthedocs.io/
Project-URL: Repository, https://github.com/ondrolexa/pywerami.git
Project-URL: Issues, https://github.com/ondrolexa/pywerami/issues
Project-URL: Changelog, https://github.com/ondrolexa/pywerami/blob/master/CHANGELOG.md
Author-email: Ondrej Lexa <lexa.ondrej@gmail.com>
Maintainer-email: Ondrej Lexa <lexa.ondrej@gmail.com>
License: MIT License
License-File: AUTHORS.md
License-File: LICENSE
Keywords: Perple_X,petrology
Classifier: Development Status :: 4 - Beta
Classifier: Intended Audience :: Science/Research
Classifier: Programming Language :: Python :: 3
Classifier: Programming Language :: Python :: 3 :: Only
Classifier: Programming Language :: Python :: 3.10
Classifier: Topic :: Scientific/Engineering
Classifier: Topic :: Utilities
Requires-Python: >=3.10
Requires-Dist: matplotlib
Requires-Dist: numpy
Requires-Dist: qtpy
Requires-Dist: scipy
Provides-Extra: dev
Requires-Dist: black; extra == 'dev'
Requires-Dist: pyqt6; extra == 'dev'
Requires-Dist: pytest; extra == 'dev'
Requires-Dist: sphinx; extra == 'dev'
Requires-Dist: sphinx-mdinclude; extra == 'dev'
Requires-Dist: sphinx-rtd-theme; extra == 'dev'
Provides-Extra: docs
Requires-Dist: sphinx; extra == 'docs'
Requires-Dist: sphinx-mdinclude; extra == 'docs'
Requires-Dist: sphinx-rtd-theme; extra == 'docs'
Provides-Extra: pyqt5
Requires-Dist: pyqt5; extra == 'pyqt5'
Provides-Extra: pyqt6
Requires-Dist: pyqt6; extra == 'pyqt6'
Provides-Extra: tests
Requires-Dist: pytest; extra == 'tests'
